giteamigration/__init__.py
giteamigration/cli.py
giteamigration/giteamigration.py
giteamigration-0.1.0a4.dist-info/AUTHORS.rst
giteamigration-0.1.0a4.dist-info/LICENSE
giteamigration-0.1.0a4.dist-info/METADATA
giteamigration-0.1.0a4.dist-info/WHEEL
giteamigration-0.1.0a4.dist-info/entry_points.txt
giteamigration-0.1.0a4.dist-info/top_level.txt
giteamigration-0.1.0a4.dist-info/RECORD
