Metadata-Version: 2.1
Name: giteamigration
Version: 0.1.0a4
Summary: Program to one way sync git repositories between supported git servers
Home-page: https://github.com/amritanshu-pandey/giteamigration
Author: Amritanshu Pandey
Author-email: email@amritanshu.in
License: MIT license
Keywords: giteamigration
Platform: UNKNOWN
Classifier: Development Status :: 2 - Pre-Alpha
Classifier: Intended Audience :: Developers
Classifier: License :: OSI Approved :: MIT License
Classifier: Natural Language :: English
Classifier: Programming Language :: Python :: 3
Classifier: Programming Language :: Python :: 3.5
Classifier: Programming Language :: Python :: 3.6
Classifier: Programming Language :: Python :: 3.7
Classifier: Programming Language :: Python :: 3.8
Requires-Python: >=3.5
Requires-Dist: Click (>=7.0)
Requires-Dist: mgsc (==0.1.0-alpha.3)
Requires-Dist: requests
Requires-Dist: GitPython
Provides-Extra: test
Requires-Dist: pytest (>=3) ; extra == 'test'
Requires-Dist: flake8 ; extra == 'test'
Requires-Dist: mypy ; extra == 'test'
